UART.srcs/sources_1/new/rx.v
`timescale 1ns / 1ps

module rx(
    input clk,
    input reset,
    input rx,
    output reg rx_done,
    output reg [7:0] rx_data 
    );
    
    parameter clk_per_bit = 87;
    
    reg receiving = 0;
    reg [7:0] rx_shift = 0;
    reg [3:0] bit_index = 0; 
    reg [15:0] count_clk = 0;
    
    always @ (posedge clk , posedge reset) begin 
        if (reset==1) begin 
            rx_done <= 0;
            count_clk <= 0;
            bit_index <= 0;
            receiving <= 0;                
            end
             
        else begin
            rx_done <= 0;
            if ( !receiving && (rx == 0) ) begin  
            receiving <= 1;
            count_clk <= 0;
            bit_index <= 0;  
            end
        else if (receiving) begin
                if (count_clk < clk_per_bit -1) begin
                bit_index <= bit_index + 1;
                count_clk <= 0;
                
                case (bit_index)
                1 : rx_shift[0] <= rx; 
                2 : rx_shift[1] <= rx;
                3 : rx_shift[2] <= rx;
                4 : rx_shift[3] <= rx;
                5 : rx_shift[4] <= rx;
                6 : rx_shift[5] <= rx;
                7 : rx_shift[6] <= rx;
                8 : rx_shift[7] <= rx;
                9 : begin
                    rx_data <= rx_shift;
                    rx_done <= 1;
                    receiving <= 0;
                    end
                endcase
             end   
           else begin
             count_clk <= count_clk + 1;
           end
        end          
     end
  end   
endmodule

UART.srcs/sources_1/new/tx.v
`timescale 1ns / 1ps

module tx(
    input clk,              // by default all the input are wire.
    input reset,
    input [7:0] tx_data,
    input tx_start,
    output reg tx,
    output reg tx_busy                 // tell the whether the system is busy or not.
    );
    
    parameter clk_per_bit = 87;          // clk_frequency(1MHz) / baud rate(11520) = clk_per_bit
    
    reg [7:0] tx_shift = 0;           // for storing the data for FSM
    reg [15:0] count_clk = 0;         // counts how many clk cycle passed for the current bit 
    reg sending = 0;                  // it tell whether the system is busy or not internally.
    reg  [3:0] bit_index =0;
    
    always @ (posedge clk , posedge reset) 
    begin
    if (reset == 1) begin 
        tx <= 1'b1;
        sending <= 0; 
        tx_busy <= 0;
        count_clk <= 0;
        bit_index <= 0;
        end
    else if (!tx_busy && tx_start) 
            begin
            tx <= 0;                   // start bit
            tx_busy <= 1;
            sending <= 1;
            tx_shift <= tx_data;
            count_clk <= 0;
            bit_index <= 0;        
            end
        else if(sending) 
            if (count_clk < clk_per_bit -1)  begin
                count_clk <= count_clk + 1;
                end
            else begin 
                count_clk <= 0;
                bit_index <= bit_index + 1;
                    case(bit_index)
                    0 : tx <= tx_shift[0];
                    1 : tx <= tx_shift[1];
                    2 : tx <= tx_shift[2];
                    3 : tx <= tx_shift[3];
                    4 : tx <= tx_shift[4];
                    5 : tx <= tx_shift[5];
                    6 : tx <= tx_shift[6];
                    7 : tx <= tx_shift[7];
                    8 : begin
                        sending <= 0;
                        tx_busy <= 0;
                        tx <= 1;                       //stop bit
                    end
                    endcase    
                end
            end
   
 endmodule

UART.srcs/sim_1/new/tb.v
`timescale 1ns/1ps

module tb;

reg clk = 0, reset = 0;
reg [7:0] tx_data = 8'h00;      // 8 bit hexadecimal initialing to 0
reg tx_start = 0;
wire tx, tx_busy;

wire rx;        //wire instead of ref becasue to connect wire-to-wire 
wire [7:0] rx_data;
wire rx_done;


initial begin 
forever #10 clk = ~clk;
end

// Transmitor module instantiates  (basically, you're creating an object )
tx tx_DUT(.clk(clk),
          .reset(reset),
          .tx_data(tx_data),
          .tx_start(tx_start),
          .tx(tx),
          .tx_busy(tx_busy)
          );

// Receiver module instantiates
rx rx_DUT(.clk(clk),
          .reset(reset),
          .rx_data(rx_data),
          .rx_done(rx_done),
          .rx(rx)
          );
          
assign rx = tx;     // connecting wire-to-wire

initial begin
$display("Starting UART Testbench");
        $dumpfile("uart.vcd");
        $dumpvars(0, tb);
#10;
reset = 1;

#20;
reset = 0;

tx_data = 8'h7A;        // 122(Z ASCII) / 16 = 7 with a remainder of 10 = 7A
tx_start = 1;
#10 tx_start = 0;

wait(rx_done);      // waits till rx receive the data i.e (rx_done == 1). / receiver finishes receiving 8 bits + stop bit
#20;                // Wait 20 time units to let signals settle before checking results

$display("Received data: %h", rx_data);

end

endmodule

UART.sim/sim_1/behav/xsim/uart.vcd
$date
   Mon Apr  7 19:00:23 2025
$end

$version
  2024.2.0
  $dumpfile ("uart.vcd") 
$end

$timescale
  1ps
$end

$scope module tb $end
$var reg 1 ! clk $end
$var reg 1 " reset $end
$var reg 8 # tx_data [7:0] $end
$var reg 1 $ tx_start $end
$var wire 1 % tx $end
$var wire 1 & tx_busy $end
$var wire 1 ' rx $end
$var wire 8 ( rx_data [7:0] $end
$var wire 1 ) rx_done $end
$scope module tx_DUT $end
$var wire 1 * clk $end
$var wire 1 + reset $end
$var wire 8 , tx_data [7:0] $end
$var wire 1 - tx_start $end
$var reg 1 . tx $end
$var reg 1 / tx_busy $end
$var reg 8 0 tx_shift [7:0] $end
$var reg 16 1 count_clk [15:0] $end
$var reg 1 2 sending $end
$var reg 4 3 bit_index [3:0] $end
$upscope $end
$scope module rx_DUT $end
$var wire 1 4 clk $end
$var wire 1 5 reset $end
$var wire 1 ' rx $end
$var reg 1 6 rx_done $end
$var reg 8 7 rx_data [7:0] $end
$var reg 1 8 receiving $end
$var reg 8 9 rx_shift [7:0] $end
$var reg 4 : bit_index [3:0] $end
$var reg 16 ; count_clk [15:0] $end
$upscope $end
$upscope $end
$enddefinitions $end

#0
$dumpvars
0!
0"
b0 #
0$
x%
x&
x'
bx (
x)
0*
0+
b0 ,
0-
x.
x/
b0 0
b0 1
02
b0 3
04
05
x6
bx 7
08
b0 9
b0 :
b0 ;
$end

#10000
1!
1"
1%
0&
1'
0)
1*
1+
1.
0/
14
15
06

#20000
0!
0*
04

#30000
1!
0"
b1111010 #
1$
0%
1&
0'
1*
0+
b1111010 ,
1-
0.
1/
b1111010 0
12
14
05

#40000
0!
0$
0*
0-
04

#50000
1!
1*
b1 1
14
18

#60000
0!
0*
04

#70000
1!
1*
b10 1
14
b1 :

#80000
0!
0*
04

#90000
1!
1*
b11 1
14
b10 :

#100000
0!
0*
04

#110000
1!
1*
b100 1
14
b11 :

#120000
0!
0*
04

#130000
1!
1*
b101 1
14
b100 :

#140000
0!
0*
04

#150000
1!
1*
b110 1
14
b101 :

#160000
0!
0*
04

#170000
1!
1*
b111 1
14
b110 :

#180000
0!
0*
04

#190000
1!
1*
b1000 1
14
b111 :

#200000
0!
0*
04

#210000
1!
1*
b1001 1
14
b1000 :

#220000
0!
0*
04

#230000
1!
1*
b1010 1
14
b1001 :

#240000
0!
0*
04

#250000
1!
b0 (
1)
1*
b1011 1
14
16
b0 7
08
b1010 :

#260000
0!
0*
04

#270000
1!
0)
1*
b1100 1
14
06
18
b0 :

#280000
0!
0*
04

#290000
1!
1*
b1101 1
14
b1 :

#300000
0!
0*
04

#310000
1!
1*
b1110 1
14
b10 :

#320000
0!
0*
04

#330000
1!
1*
b1111 1
14
b11 :

#340000
0!
0*
04

#350000
1!
1*
b10000 1
14
b100 :

#360000
0!
0*
04

#370000
1!
1*
b10001 1
14
b101 :

#380000
0!
0*
04

#390000
1!
1*
b10010 1
14
b110 :

#400000
0!
0*
04

#410000
1!
1*
b10011 1
14
b111 :

#420000
0!
0*
04

#430000
1!
1*
b10100 1
14
b1000 :

#440000
0!
0*
04

#450000
1!
1*
b10101 1
14
b1001 :

#460000
0!
0*
04

#470000
1!
1)
1*
b10110 1
14
16
08
b1010 :

#480000
0!
0*
04

#490000
1!
0)
1*
b10111 1
14
06
18
b0 :

#500000
0!
0*
04

#510000
1!
1*
b11000 1
14
b1 :

#520000
0!
0*
04

#530000
1!
1*
b11001 1
14
b10 :

#540000
0!
0*
04

#550000
1!
1*
b11010 1
14
b11 :

#560000
0!
0*
04

#570000
1!
1*
b11011 1
14
b100 :

#580000
0!
0*
04

#590000
1!
1*
b11100 1
14
b101 :

#600000
0!
0*
04

#610000
1!
1*
b11101 1
14
b110 :

#620000
0!
0*
04

#630000
1!
1*
b11110 1
14
b111 :

#640000
0!
0*
04

#650000
1!
1*
b11111 1
14
b1000 :

#660000
0!
0*
04

#670000
1!
1*
b100000 1
14
b1001 :

#680000
0!
0*
04

#690000
1!
1)
1*
b100001 1
14
16
08
b1010 :

#700000
0!
0*
04

#710000
1!
0)
1*
b100010 1
14
06
18
b0 :

#720000
0!
0*
04

#730000
1!
1*
b100011 1
14
b1 :

#740000
0!
0*
04

#750000
1!
1*
b100100 1
14
b10 :

#760000
0!
0*
04

#770000
1!
1*
b100101 1
14
b11 :

#780000
0!
0*
04

#790000
1!
1*
b100110 1
14
b100 :

#800000
0!
0*
04

#810000
1!
1*
b100111 1
14
b101 :

#820000
0!
0*
04

#830000
1!
1*
b101000 1
14
b110 :

#840000
0!
0*
04

#850000
1!
1*
b101001 1
14
b111 :

#860000
0!
0*
04

#870000
1!
1*
b101010 1
14
b1000 :

#880000
0!
0*
04

#890000
1!
1*
b101011 1
14
b1001 :

#900000
0!
0*
04

#910000
1!
1)
1*
b101100 1
14
16
08
b1010 :

#920000
0!
0*
04

#930000
1!
0)
1*
b101101 1
14
06
18
b0 :

#940000
0!
0*
04

#950000
1!
1*
b101110 1
14
b1 :

#960000
0!
0*
04

#970000
1!
1*
b101111 1
14
b10 :

#980000
0!
0*
04

#990000
1!
1*
b110000 1
14
b11 :
